Workbook

Sheet brands
A1: brand_id | B1: brand_name
A2: 1 | B2: Electra
A3: 2 | B3: Haro
A4: 3 | B4: Heller
A5: 4 | B5: Pure Cycles
A6: 5 | B6: Ritchey
A7: 6 | B7: Strider
A8: 7 | B8: Sun Bicycles
A9: 8 | B9: Surly
A10: 9 | B10: Trek

Sheet categories
A1: category_id | B1: category_name
A2: 1 | B2: Children Bicycles
A3: 2 | B3: Comfort Bicycles
A4: 3 | B4: Cruisers Bicycles
A5: 4 | B5: Cyclocross Bicycles
A6: 5 | B6: Electric Bikes
A7: 6 | B7: Mountain Bikes
A8: 7 | B8: Road Bikes

Sheet customers
A1: customer_id | B1: first_name | C1: last_name | D1: phone | E1: email | F1: street | G1: city | H1: state | I1: zip_code
A2: 1 | B2: Debra | C2: Burks | D2: NA | E2: debra.burks@yahoo.com | F2: 9273 Thorne Ave. | G2: Orchard Park | H2: NY | I2: 14127
A3: 2 | B3: Kasha | C3: Todd | D3: NA | E3: kasha.todd@yahoo.com | F3: 910 Vine Street | G3: Campbell | H3: CA | I3: 95008
A4: 3 | B4: Tameka | C4: Fisher | D4: NA | E4: tameka.fisher@aol.com | F4: 769C Honey Creek St. | G4: Redondo Beach | H4: CA | I4: 90278
A5: 4 | B5: Daryl | C5: Spence | D5: NA | E5: daryl.spence@aol.com | F5: 988 Pearl Lane | G5: Uniondale | H5: NY | I5: 11553
A6: 5 | B6: Charolette | C6: Rice | D6: (916) 381-6003 | E6: charolette.rice@msn.com | F6: 107 River Dr. | G6: Sacramento | H6: CA | I6: 95820
A7: 6 | B7: Lyndsey | C7: Bean | D7: NA | E7: lyndsey.bean@hotmail.com | F7: 769 West Road | G7: Fairport | H7: NY | I7: 14450
A8: 7 | B8: Latasha | C8: Hays | D8: (716) 986-3359 | E8: latasha.hays@hotmail.com | F8: 7014 Manor Station Rd. | G8: Buffalo | H8: NY | I8: 14215
A9: 8 | B9: Jacquline | C9: Duncan | D9: NA | E9: jacquline.duncan@yahoo.com | F9: 15 Brown St. | G9: Jackson Heights | H9: NY | I9: 11372
A10: 9 | B10: Genoveva | C10: Baldwin | D10: NA | E10: genoveva.baldwin@msn.com | F10: 8550 Spruce Drive | G10: Port Washington | H10: NY | I10: 11050
A11: 10 | B11: Pamelia | C11: Newman | D11: NA | E11: pamelia.newman@gmail.com | F11: 476 Chestnut Ave. | G11: Monroe | H11: NY | I11: 10950
A12: 11 | B12: Deshawn | C12: Mendoza | D12: NA | E12: deshawn.mendoza@yahoo.com | F12: 8790 Cobblestone Street | G12: Monsey | H12: NY | I12: 10952
A13: 12 | B13: Robby | C13: Sykes | D13: (516) 583-7761 | E13: robby.sykes@hotmail.com | F13: 486 Rock Maple Street | G13: Hempstead | H13: NY | I13: 11550
... A1446: 1445 | B1446: Ester | C1446: Acevedo | D1446: NA | E1446: ester.acevedo@gmail.com | F1446: 671 Miles Court | G1446: San Lorenzo | H1446: CA | I1446: 94580

Sheet orders
A1: order_id | B1: customer_id | C1: order_status | D1: order_date | E1: required_date | F1: shipped_date | G1: store_id | H1: staff_id | I1: order_status
A2: 1 | B2: 259 | C2: 4 | D2: 42370 | E2: 42372 | F2: 42372 | G2: 1 | H2: 2 | I2: =IF(F2="NA","Pending",IF(OR(E2=F2,E2<F2),"Shipped","Delivered")) -> Shipped
A3: 2 | B3: 1212 | C3: 4 | D3: 42370 | E3: 42373 | F3: 42372 | G3: 2 | H3: 6 | I3: =IF(F3="NA","Pending",IF(OR(E3=F3,E3<F3),"Shipped","Delivered")) -> Delivered
A4: 3 | B4: 523 | C4: 4 | D4: 42371 | E4: 42374 | F4: 42372 | G4: 2 | H4: 7 | I4: =IF(F4="NA","Pending",IF(OR(E4=F4,E4<F4),"Shipped","Delivered")) -> Delivered
A5: 4 | B5: 175 | C5: 4 | D5: 42372 | E5: 42373 | F5: 42374 | G5: 1 | H5: 3 | I5: =IF(F5="NA","Pending",IF(OR(E5=F5,E5<F5),"Shipped","Delivered")) -> Shipped
A6: 5 | B6: 1324 | C6: 4 | D6: 42372 | E6: 42375 | F6: 42375 | G6: 2 | H6: 6 | I6: =IF(F6="NA","Pending",IF(OR(E6=F6,E6<F6),"Shipped","Delivered")) -> Shipped
A7: 6 | B7: 94 | C7: 4 | D7: 42373 | E7: 42376 | F7: 42374 | G7: 2 | H7: 6 | I7: =IF(F7="NA","Pending",IF(OR(E7=F7,E7<F7),"Shipped","Delivered")) -> Delivered
A8: 7 | B8: 324 | C8: 4 | D8: 42373 | E8: 42376 | F8: 42374 | G8: 2 | H8: 6 | I8: =IF(F8="NA","Pending",IF(OR(E8=F8,E8<F8),"Shipped","Delivered")) -> Delivered
A9: 8 | B9: 1204 | C9: 4 | D9: 42373 | E9: 42374 | F9: 42374 | G9: 2 | H9: 7 | I9: =IF(F9="NA","Pending",IF(OR(E9=F9,E9<F9),"Shipped","Delivered")) -> Shipped
A10: 9 | B10: 60 | C10: 4 | D10: 42374 | E10: 42377 | F10: 42377 | G10: 1 | H10: 2 | I10: =IF(F10="NA","Pending",IF(OR(E10=F10,E10<F10),"Shipped","Delivered")) -> Shipped
A11: 10 | B11: 442 | C11: 4 | D11: 42374 | E11: 42375 | F11: 42375 | G11: 2 | H11: 6 | I11: =IF(F11="NA","Pending",IF(OR(E11=F11,E11<F11),"Shipped","Delivered")) -> Shipped
A12: 11 | B12: 1326 | C12: 4 | D12: 42374 | E12: 42377 | F12: 42376 | G12: 2 | H12: 7 | I12: =IF(F12="NA","Pending",IF(OR(E12=F12,E12<F12),"Shipped","Delivered")) -> Delivered
A13: 12 | B13: 91 | C13: 4 | D13: 42375 | E13: 42377 | F13: 42378 | G13: 1 | H13: 2 | I13: =IF(F13="NA","Pending",IF(OR(E13=F13,E13<F13),"Shipped","Delivered")) -> Shipped
... A70: 69 | B70: 1413 | C70: 4 | D70: 42410 | E70: 42412 | F70: 42411 | G70: 2 | H70: 7 | I70: =IF(F70="NA","Pending",IF(OR(E70=F70,E70<F70),"Shipped","Delivered")) -> Delivered
A71: 70 | B71: 50 | C71: 3 | D71: 42411 | E71: 42411 | F71: NA | G71: 3 | H71: 9 | I71: =IF(F71="NA","Pending",IF(OR(E71=F71,E71<F71),"Shipped","Delivered")) -> Pending
A72: 71 | B72: 797 | C72: 4 | D72: 42411 | E72: 42414 | F72: 42412 | G72: 2 | H72: 7 | I72: =IF(F72="NA","Pending",IF(OR(E72=F72,E72<F72),"Shipped","Delivered")) -> Delivered
A73: 72 | B73: 1386 | C73: 4 | D73: 42412 | E73: 42415 | F73: 42413 | G73: 1 | H73: 2 | I73: =IF(F73="NA","Pending",IF(OR(E73=F73,E73<F73),"Shipped","Delivered")) -> Delivered
A74: 73 | B74: 612 | C74: 4 | D74: 42412 | E74: 42415 | F74: 42414 | G74: 2 | H74: 7 | I74: =IF(F74="NA","Pending",IF(OR(E74=F74,E74<F74),"Shipped","Delivered")) -> Delivered
A75: 74 | B75: 264 | C75: 4 | D75: 42413 | E75: 42415 | F75: 42415 | G75: 2 | H75: 7 | I75: =IF(F75="NA","Pending",IF(OR(E75=F75,E75<F75),"Shipped","Delivered")) -> Shipped
A76: 75 | B76: 587 | C76: 4 | D76: 42414 | E76: 42415 | F76: 42417 | G76: 2 | H76: 6 | I76: =IF(F76="NA","Pending",IF(OR(E76=F76,E76<F76),"Shipped","Delivered")) -> Shipped
A77: 76 | B77: 9 | C77: 3 | D77: 42416 | E77: 42416 | F77: NA | G77: 2 | H77: 6 | I77: =IF(F77="NA","Pending",IF(OR(E77=F77,E77<F77),"Shipped","Delivered")) -> Pending
A78: 77 | B78: 385 | C78: 4 | D78: 42416 | E78: 42419 | F78: 42419 | G78: 1 | H78: 2 | I78: =IF(F78="NA","Pending",IF(OR(E78=F78,E78<F78),"Shipped","Delivered")) -> Shipped
A79: 78 | B79: 1182 | C79: 4 | D79: 42416 | E79: 42418 | F79: 42419 | G79: 2 | H79: 7 | I79: =IF(F79="NA","Pending",IF(OR(E79=F79,E79<F79),"Shipped","Delivered")) -> Shipped
A80: 79 | B80: 529 | C80: 4 | D80: 42417 | E80: 42420 | F80: 42420 | G80: 1 | H80: 3 | I80: =IF(F80="NA","Pending",IF(OR(E80=F80,E80<F80),"Shipped","Delivered")) -> Shipped
A81: 80 | B81: 397 | C81: 4 | D81: 42417 | E81: 42420 | F81: 42419 | G81: 2 | H81: 6 | I81: =IF(F81="NA","Pending",IF(OR(E81=F81,E81<F81),"Shipped","Delivered")) -> Delivered
A82: 81 | B82: 521 | C82: 4 | D82: 42417 | E82: 42419 | F82: 42418 | G82: 2 | H82: 6 | I82: =IF(F82="NA","Pending",IF(OR(E82=F82,E82<F82),"Shipped","Delivered")) -> Delivered
A83: 82 | B83: 1223 | C83: 4 | D83: 42418 | E83: 42421 | F83: 42420 | G83: 2 | H83: 6 | I83: =IF(F83="NA","Pending",IF(OR(E83=F83,E83<F83),"Shipped","Delivered")) -> Delivered
A84: 83 | B84: 393 | C84: 4 | D84: 42419 | E84: 42420 | F84: 42420 | G84: 1 | H84: 3 | I84: =IF(F84="NA","Pending",IF(OR(E84=F84,E84<F84),"Shipped","Delivered")) -> Shipped
A85: 84 | B85: 317 | C85: 4 | D85: 42420 | E85: 42422 | F85: 42421 | G85: 2 | H85: 7 | I85: =IF(F85="NA","Pending",IF(OR(E85=F85,E85<F85),"Shipped","Delivered")) -> Delivered
A86: 85 | B86: 1174 | C86: 4 | D86: 42420 | E86: 42423 | F86: 42421 | G86: 2 | H86: 7 | I86: =IF(F86="NA","Pending",IF(OR(E86=F86,E86<F86),"Shipped","Delivered")) -> Delivered
A87: 86 | B87: 276 | C87: 4 | D87: 42421 | E87: 42422 | F87: 42423 | G87: 2 | H87: 7 | I87: =IF(F87="NA","Pending",IF(OR(E87=F87,E87<F87),"Shipped","Delivered")) -> Shipped
A88: 87 | B88: 516 | C88: 4 | D88: 42421 | E88: 42422 | F88: 42423 | G88: 2 | H88: 6 | I88: =IF(F88="NA","Pending",IF(OR(E88=F88,E88<F88),"Shipped","Delivered")) -> Shipped
A89: 88 | B89: 1069 | C89: 4 | D89: 42421 | E89: 42422 | F89: 42423 | G89: 2 | H89: 6 | I89: =IF(F89="NA","Pending",IF(OR(E89=F89,E89<F89),"Shipped","Delivered")) -> Shipped
... A158: 157 | B158: 43 | C158: 4 | D158: 42463 | E158: 42466 | F158: 42466 | G158: 3 | H158: 8 | I158: =IF(F158="NA","Pending",IF(OR(E158=F158,E158<F158),"Shipped","Delivered")) -> Shipped
A159: 158 | B159: 117 | C159: 3 | D159: 42464 | E159: 42464 | F159: NA | G159: 3 | H159: 9 | I159: =IF(F159="NA","Pending",IF(OR(E159=F159,E159<F159),"Shipped","Delivered")) -> Pending
A160: 159 | B160: 32 | C160: 4 | D160: 42464 | E160: 42466 | F160: 42466 | G160: 1 | H160: 2 | I160: =IF(F160="NA","Pending",IF(OR(E160=F160,E160<F160),"Shipped","Delivered")) -> Shipped
A161: 160 | B161: 205 | C161: 4 | D161: 42464 | E161: 42466 | F161: 42466 | G161: 2 | H161: 7 | I161: =IF(F161="NA","Pending",IF(OR(E161=F161,E161<F161),"Shipped","Delivered")) -> Shipped
A162: 161 | B162: 251 | C162: 4 | D162: 42464 | E162: 42467 | F162: 42465 | G162: 2 | H162: 7 | I162: =IF(F162="NA","Pending",IF(OR(E162=F162,E162<F162),"Shipped","Delivered")) -> Delivered
A163: 162 | B163: 31 | C163: 4 | D163: 42466 | E163: 42468 | F163: 42467 | G163: 1 | H163: 3 | I163: =IF(F163="NA","Pending",IF(OR(E163=F163,E163<F163),"Shipped","Delivered")) -> Delivered
A164: 163 | B164: 1325 | C164: 4 | D164: 42466 | E164: 42467 | F164: 42467 | G164: 2 | H164: 7 | I164: =IF(F164="NA","Pending",IF(OR(E164=F164,E164<F164),"Shipped","Delivered")) -> Shipped
A165: 164 | B165: 610 | C165: 4 | D165: 42467 | E165: 42468 | F165: 42469 | G165: 2 | H165: 7 | I165: =IF(F165="NA","Pending",IF(OR(E165=F165,E165<F165),"Shipped","Delivered")) -> Shipped
A166: 165 | B166: 574 | C166: 4 | D166: 42468 | E166: 42470 | F166: 42470 | G166: 1 | H166: 3 | I166: =IF(F166="NA","Pending",IF(OR(E166=F166,E166<F166),"Shipped","Delivered")) -> Shipped
A167: 166 | B167: 338 | C167: 4 | D167: 42468 | E167: 42471 | F167: 42471 | G167: 2 | H167: 6 | I167: =IF(F167="NA","Pending",IF(OR(E167=F167,E167<F167),"Shipped","Delivered")) -> Shipped
A168: 167 | B168: 1034 | C168: 4 | D168: 42468 | E168: 42469 | F168: 42471 | G168: 2 | H168: 7 | I168: =IF(F168="NA","Pending",IF(OR(E168=F168,E168<F168),"Shipped","Delivered")) -> Shipped
A169: 168 | B169: 1147 | C169: 4 | D169: 42469 | E169: 42472 | F169: 42471 | G169: 1 | H169: 3 | I169: =IF(F169="NA","Pending",IF(OR(E169=F169,E169<F169),"Shipped","Delivered")) -> Delivered
A170: 169 | B170: 99 | C170: 4 | D170: 42470 | E170: 42471 | F170: 42471 | G170: 2 | H170: 7 | I170: =IF(F170="NA","Pending",IF(OR(E170=F170,E170<F170),"Shipped","Delivered")) -> Shipped
A171: 170 | B171: 1200 | C171: 4 | D171: 42470 | E171: 42471 | F171: 42473 | G171: 2 | H171: 7 | I171: =IF(F171="NA","Pending",IF(OR(E171=F171,E171<F171),"Shipped","Delivered")) -> Shipped
... A185: 184 | B185: 134 | C185: 4 | D185: 42479 | E185: 42481 | F185: 42482 | G185: 2 | H185: 7 | I185: =IF(F185="NA","Pending",IF(OR(E185=F185,E185<F185),"Shipped","Delivered")) -> Shipped
A186: 185 | B186: 24 | C186: 3 | D186: 42480 | E186: 42480 | F186: NA | G186: 1 | H186: 2 | I186: =IF(F186="NA","Pending",IF(OR(E186=F186,E186<F186),"Shipped","Delivered")) -> Pending
A187: 186 | B187: 1127 | C187: 4 | D187: 42481 | E187: 42482 | F187: 42484 | G187: 2 | H187: 6 | I187: =IF(F187="NA","Pending",IF(OR(E187=F187,E187<F187),"Shipped","Delivered")) -> Shipped
A188: 187 | B188: 183 | C188: 4 | D188: 42482 | E188: 42483 | F188: 42484 | G188: 2 | H188: 6 | I188: =IF(F188="NA","Pending",IF(OR(E188=F188,E188<F188),"Shipped","Delivered")) -> Shipped
A189: 188 | B189: 390 | C189: 4 | D189: 42482 | E189: 42483 | F189: 42485 | G189: 2 | H189: 6 | I189: =IF(F189="NA","Pending",IF(OR(E189=F189,E189<F189),"Shipped","Delivered")) -> Shipped
A190: 189 | B190: 1288 | C190: 4 | D190: 42483 | E190: 42484 | F190: 42486 | G190: 1 | H190: 2 | I190: =IF(F190="NA","Pending",IF(OR(E190=F190,E190<F190),"Shipped","Delivered")) -> Shipped
A191: 190 | B191: 98 | C191: 4 | D191: 42483 | E191: 42485 | F191: 42485 | G191: 2 | H191: 6 | I191: =IF(F191="NA","Pending",IF(OR(E191=F191,E191<F191),"Shipped","Delivered")) -> Shipped
A192: 191 | B192: 919 | C192: 4 | D192: 42487 | E192: 42488 | F192: 42488 | G192: 1 | H192: 2 | I192: =IF(F192="NA","Pending",IF(OR(E192=F192,E192<F192),"Shipped","Delivered")) -> Shipped
A193: 192 | B193: 728 | C193: 4 | D193: 42487 | E193: 42488 | F193: 42489 | G193: 2 | H193: 7 | I193: =IF(F193="NA","Pending",IF(OR(E193=F193,E193<F193),"Shipped","Delivered")) -> Shipped
A194: 193 | B194: 1366 | C194: 4 | D194: 42488 | E194: 42490 | F194: 42490 | G194: 1 | H194: 3 | I194: =IF(F194="NA","Pending",IF(OR(E194=F194,E194<F194),"Shipped","Delivered")) -> Shipped
A195: 194 | B195: 558 | C195: 4 | D195: 42488 | E195: 42490 | F195: 42491 | G195: 2 | H195: 7 | I195: =IF(F195="NA","Pending",IF(OR(E195=F195,E195<F195),"Shipped","Delivered")) -> Shipped
A196: 195 | B196: 727 | C196: 4 | D196: 42488 | E196: 42491 | F196: 42491 | G196: 2 | H196: 7 | I196: =IF(F196="NA","Pending",IF(OR(E196=F196,E196<F196),"Shipped","Delivered")) -> Shipped
A197: 196 | B197: 1247 | C197: 4 | D197: 42488 | E197: 42490 | F197: 42491 | G197: 2 | H197: 6 | I197: =IF(F197="NA","Pending",IF(OR(E197=F197,E197<F197),"Shipped","Delivered")) -> Shipped
A198: 197 | B198: 127 | C198: 4 | D198: 42490 | E198: 42493 | F198: 42493 | G198: 2 | H198: 7 | I198: =IF(F198="NA","Pending",IF(OR(E198=F198,E198<F198),"Shipped","Delivered")) -> Shipped
... A239: 238 | B239: 1350 | C239: 4 | D239: 42516 | E239: 42519 | F239: 42519 | G239: 2 | H239: 6 | I239: =IF(F239="NA","Pending",IF(OR(E239=F239,E239<F239),"Shipped","Delivered")) -> Shipped
A240: 239 | B240: 13 | C240: 3 | D240: 42517 | E240: 42517 | F240: NA | G240: 3 | H240: 9 | I240: =IF(F240="NA","Pending",IF(OR(E240=F240,E240<F240),"Shipped","Delivered")) -> Pending
A241: 240 | B241: 65 | C241: 4 | D241: 42517 | E241: 42519 | F241: 42520 | G241: 2 | H241: 6 | I241: =IF(F241="NA","Pending",IF(OR(E241=F241,E241<F241),"Shipped","Delivered")) -> Shipped
A242: 241 | B242: 1082 | C242: 4 | D242: 42517 | E242: 42519 | F242: 42519 | G242: 2 | H242: 7 | I242: =IF(F242="NA","Pending",IF(OR(E242=F242,E242<F242),"Shipped","Delivered")) -> Shipped
A243: 242 | B243: 1168 | C243: 4 | D243: 42517 | E243: 42520 | F243: 42520 | G243: 2 | H243: 7 | I243: =IF(F243="NA","Pending",IF(OR(E243=F243,E243<F243),"Shipped","Delivered")) -> Shipped
A244: 243 | B244: 802 | C244: 4 | D244: 42517 | E244: 42520 | F244: 42518 | G244: 3 | H244: 8 | I244: =IF(F244="NA","Pending",IF(OR(E244=F244,E244<F244),"Shipped","Delivered")) -> Delivered
A245: 244 | B245: 956 | C245: 4 | D245: 42518 | E245: 42519 | F245: 42519 | G245: 2 | H245: 6 | I245: =IF(F245="NA","Pending",IF(OR(E245=F245,E245<F245),"Shipped","Delivered")) -> Shipped
A246: 245 | B246: 223 | C246: 4 | D246: 42519 | E246: 42521 | F246: 42520 | G246: 2 | H246: 7 | I246: =IF(F246="NA","Pending",IF(OR(E246=F246,E246<F246),"Shipped","Delivered")) -> Delivered
A247: 246 | B247: 17 | C247: 3 | D247: 42520 | E247: 42520 | F247: NA | G247: 2 | H247: 6 | I247: =IF(F247="NA","Pending",IF(OR(E247=F247,E247<F247),"Shipped","Delivered")) -> Pending
A248: 247 | B248: 928 | C248: 4 | D248: 42520 | E248: 42522 | F248: 42522 | G248: 1 | H248: 3 | I248: =IF(F248="NA","Pending",IF(OR(E248=F248,E248<F248),"Shipped","Delivered")) -> Shipped
A249: 248 | B249: 1376 | C249: 4 | D249: 42520 | E249: 42522 | F249: 42521 | G249: 2 | H249: 7 | I249: =IF(F249="NA","Pending",IF(OR(E249=F249,E249<F249),"Shipped","Delivered")) -> Delivered
A250: 249 | B250: 145 | C250: 4 | D250: 42522 | E250: 42525 | F250: 42525 | G250: 2 | H250: 6 | I250: =IF(F250="NA","Pending",IF(OR(E250=F250,E250<F250),"Shipped","Delivered")) -> Shipped
A251: 250 | B251: 150 | C251: 4 | D251: 42522 | E251: 42523 | F251: 42525 | G251: 2 | H251: 7 | I251: =IF(F251="NA","Pending",IF(OR(E251=F251,E251<F251),"Shipped","Delivered")) -> Shipped
A252: 251 | B252: 851 | C252: 4 | D252: 42522 | E252: 42525 | F252: 42525 | G252: 2 | H252: 7 | I252: =IF(F252="NA","Pending",IF(OR(E252=F252,E252<F252),"Shipped","Delivered")) -> Shipped
A253: 252 | B253: 66 | C253: 4 | D253: 42522 | E253: 42525 | F253: 42523 | G253: 3 | H253: 8 | I253: =IF(F253="NA","Pending",IF(OR(E253=F253,E253<F253),"Shipped","Delivered")) -> Delivered
A254: 253 | B254: 1267 | C254: 4 | D254: 42523 | E254: 42526 | F254: 42526 | G254: 2 | H254: 6 | I254: =IF(F254="NA","Pending",IF(OR(E254=F254,E254<F254),"Shipped","Delivered")) -> Shipped
A255: 254 | B255: 510 | C255: 4 | D255: 42524 | E255: 42527 | F255: 42526 | G255: 2 | H255: 7 | I255: =IF(F255="NA","Pending",IF(OR(E255=F255,E255<F255),"Shipped","Delivered")) -> Delivered
A256: 255 | B256: 801 | C256: 4 | D256: 42524 | E256: 42527 | F256: 42526 | G256: 2 | H256: 7 | I256: =IF(F256="NA","Pending",IF(OR(E256=F256,E256<F256),"Shipped","Delivered")) -> Delivered
A257: 256 | B257: 26 | C257: 4 | D257: 42525 | E257: 42526 | F257: 42528 | G257: 2 | H257: 7 | I257: =IF(F257="NA","Pending",IF(OR(E257=F257,E257<F257),"Shipped","Delivered")) -> Shipped
A258: 257 | B258: 1314 | C258: 4 | D258: 42526 | E258: 42527 | F258: 42529 | G258: 1 | H258: 3 | I258: =IF(F258="NA","Pending",IF(OR(E258=F258,E258<F258),"Shipped","Delivered")) -> Shipped
A259: 258 | B259: 107 | C259: 4 | D259: 42527 | E259: 42528 | F259: 42528 | G259: 2 | H259: 7 | I259: =IF(F259="NA","Pending",IF(OR(E259=F259,E259<F259),"Shipped","Delivered")) -> Shipped
... A264: 263 | B264: 1322 | C264: 4 | D264: 42530 | E264: 42531 | F264: 42533 | G264: 2 | H264: 6 | I264: =IF(F264="NA","Pending",IF(OR(E264=F264,E264<F264),"Shipped","Delivered")) -> Shipped
A265: 264 | B265: 5 | C265: 3 | D265: 42531 | E265: 42531 | F265: NA | G265: 1 | H265: 3 | I265: =IF(F265="NA","Pending",IF(OR(E265=F265,E265<F265),"Shipped","Delivered")) -> Pending
A266: 265 | B266: 682 | C266: 4 | D266: 42531 | E266: 42533 | F266: 42532 | G266: 2 | H266: 7 | I266: =IF(F266="NA","Pending",IF(OR(E266=F266,E266<F266),"Shipped","Delivered")) -> Delivered
A267: 266 | B267: 933 | C267: 4 | D267: 42531 | E267: 42534 | F267: 42534 | G267: 2 | H267: 7 | I267: =IF(F267="NA","Pending",IF(OR(E267=F267,E267<F267),"Shipped","Delivered")) -> Shipped
A268: 267 | B268: 282 | C268: 4 | D268: 42532 | E268: 42535 | F268: 42535 | G268: 1 | H268: 3 | I268: =IF(F268="NA","Pending",IF(OR(E268=F268,E268<F268),"Shipped","Delivered")) -> Shipped
A269: 268 | B269: 540 | C269: 4 | D269: 42532 | E269: 42535 | F269: 42533 | G269: 1 | H269: 3 | I269: =IF(F269="NA","Pending",IF(OR(E269=F269,E269<F269),"Shipped","Delivered")) -> Delivered
A270: 269 | B270: 764 | C270: 4 | D270: 42533 | E270: 42534 | F270: 42536 | G270: 2 | H270: 6 | I270: =IF(F270="NA","Pending",IF(OR(E270=F270,E270<F270),"Shipped","Delivered")) -> Shipped
A271: 270 | B271: 879 | C271: 4 | D271: 42533 | E271: 42536 | F271: 42534 | G271: 2 | H271: 7 | I271: =IF(F271="NA","Pending",IF(OR(E271=F271,E271<F271),"Shipped","Delivered")) -> Delivered
A272: 271 | B272: 350 | C272: 4 | D272: 42534 | E272: 42537 | F272: 42535 | G272: 2 | H272: 7 | I272: =IF(F272="NA","Pending",IF(OR(E272=F272,E272<F272),"Shipped","Delivered")) -> Delivered
A273: 272 | B273: 497 | C273: 4 | D273: 42536 | E273: 42539 | F273: 42537 | G273: 2 | H273: 7 | I273: =IF(F273="NA","Pending",IF(OR(E273=F273,E273<F273),"Shipped","Delivered")) -> Delivered
A274: 273 | B274: 1340 | C274: 4 | D274: 42537 | E274: 42540 | F274: 42538 | G274: 2 | H274: 7 | I274: =IF(F274="NA","Pending",IF(OR(E274=F274,E274<F274),"Shipped","Delivered")) -> Delivered
A275: 274 | B275: 411 | C275: 4 | D275: 42538 | E275: 42541 | F275: 42539 | G275: 2 | H275: 7 | I275: =IF(F275="NA","Pending",IF(OR(E275=F275,E275<F275),"Shipped","Delivered")) -> Delivered
A276: 275 | B276: 1341 | C276: 4 | D276: 42538 | E276: 42540 | F276: 42539 | G276: 2 | H276: 7 | I276: =IF(F276="NA","Pending",IF(OR(E276=F276,E276<F276),"Shipped","Delivered")) -> Delivered
A277: 276 | B277: 1227 | C277: 4 | D277: 42539 | E277: 42540 | F277: 42540 | G277: 2 | H277: 6 | I277: =IF(F277="NA","Pending",IF(OR(E277=F277,E277<F277),"Shipped","Delivered")) -> Shipped
... A349: 348 | B349: 907 | C349: 4 | D349: 42584 | E349: 42587 | F349: 42586 | G349: 3 | H349: 9 | I349: =IF(F349="NA","Pending",IF(OR(E349=F349,E349<F349),"Shipped","Delivered")) -> Delivered
A350: 349 | B350: 30 | C350: 3 | D350: 42585 | E350: 42585 | F350: NA | G350: 1 | H350: 3 | I350: =IF(F350="NA","Pending",IF(OR(E350=F350,E350<F350),"Shipped","Delivered")) -> Pending
A351: 350 | B351: 31 | C351: 3 | D351: 42585 | E351: 42585 | F351: NA | G351: 1 | H351: 3 | I351: =IF(F351="NA","Pending",IF(OR(E351=F351,E351<F351),"Shipped","Delivered")) -> Pending
A352: 351 | B352: 1307 | C352: 4 | D352: 42585 | E352: 42588 | F352: 42586 | G352: 1 | H352: 2 | I352: =IF(F352="NA","Pending",IF(OR(E352=F352,E352<F352),"Shipped","Delivered")) -> Delivered
...

Sheet Pivot
A3: Row Labels | B3: Sum of total_price
A4: Children Bicycles | B4: 292189.2
A5: Comfort Bicycles | B5: 394020.1
A6: Cruisers Bicycles | B6: 995032.62
A7: Cyclocross Bicycles | B7: 711011.84
A8: Electric Bikes | B8: 916684.78
A9: Mountain Bikes | B9: 2715079.5
A10: Road Bikes | B10: 1665098.5
A11: Grand Total | B11: 7689116.6

Sheet order_items
A1: order_id | B1: item_id | C1: product_id | D1: product_name | E1: category_id | F1: category_name | G1: quantity | H1: list_price | I1: discount | J1: total_price | K1: Z-score
A2: 1 | B2: 1 | C2: 20 | D2: =VLOOKUP($C2,products!$A$1:$F$322,MATCH(order_items!$D$1,products!$A$1:$F$1,0),FALSE) -> Electra Townie Original 7D EQ - Women's - 2016 | E2: =VLOOKUP($C2,products!$A$1:$F$322,MATCH(order_items!$E$1,products!$A$1:$F$1,0),FALSE) -> 3 | F2: =VLOOKUP($E2,categories!$A$1:$B$8,MATCH(order_items!$F$1,categories!$A$1:$B$1,0),FALSE) -> Cruisers Bicycles | G2: 1 | H2: 599.99 | I2: 0.2 | J2: =G2*H2*(1-I2) -> 479.992 | K2: =($H2-$M$7)/$M$9 -> -0.45297424
A3: 1 | B3: 2 | C3: 8 | D3: =VLOOKUP($C3,products!$A$1:$F$322,MATCH(order_items!$D$1,products!$A$1:$F$1,0),FALSE) -> Trek Remedy 29 Carbon Frameset - 2016 | E3: =VLOOKUP($C3,products!$A$1:$F$322,MATCH(order_items!$E$1,products!$A$1:$F$1,0),FALSE) -> 6 | F3: =VLOOKUP($E3,categories!$A$1:$B$8,MATCH(order_items!$F$1,categories!$A$1:$B$1,0),FALSE) -> Mountain Bikes | G3: 2 | H3: 1799.99 | I3: 0.07 | J3: =G3*H3*(1-I3) -> 3347.9814 | K3: =($H3-$M$7)/$M$9 -> 0.43416993
A4: 1 | B4: 3 | C4: 10 | D4: =VLOOKUP($C4,products!$A$1:$F$322,MATCH(order_items!$D$1,products!$A$1:$F$1,0),FALSE) -> Surly Straggler - 2016 | E4: =VLOOKUP($C4,products!$A$1:$F$322,MATCH(order_items!$E$1,products!$A$1:$F$1,0),FALSE) -> 4 | F4: =VLOOKUP($E4,categories!$A$1:$B$8,MATCH(order_items!$F$1,categories!$A$1:$B$1,0),FALSE) -> Cyclocross Bicycles | G4: 2 | H4: 1549 | I4: 0.05 | J4: =G4*H4*(1-I4) -> 2943.1 | K4: =($H4-$M$7)/$M$9 -> 0.24861633
A5: 1 | B5: 4 | C5: 16 | D5: =VLOOKUP($C5,products!$A$1:$F$322,MATCH(order_items!$D$1,products!$A$1:$F$1,0),FALSE) -> Electra Townie Original 7D EQ - 2016 | E5: =VLOOKUP($C5,products!$A$1:$F$322,MATCH(order_items!$E$1,products!$A$1:$F$1,0),FALSE) -> 3 | F5: =VLOOKUP($E5,categories!$A$1:$B$8,MATCH(order_items!$F$1,categories!$A$1:$B$1,0),FALSE) -> Cruisers Bicycles | G5: 2 | H5: 599.99 | I5: 0.05 | J5: =G5*H5*(1-I5) -> 1139.981 | K5: =($H5-$M$7)/$M$9 -> -0.45297424 | L5: Outliers In Pricing
A6: 1 | B6: 5 | C6: 4 | D6: =VLOOKUP($C6,products!$A$1:$F$322,MATCH(order_items!$D$1,products!$A$1:$F$1,0),FALSE) -> Trek Fuel EX 8 29 - 2016 | E6: =VLOOKUP($C6,products!$A$1:$F$322,MATCH(order_items!$E$1,products!$A$1:$F$1,0),FALSE) -> 6 | F6: =VLOOKUP($E6,categories!$A$1:$B$8,MATCH(order_items!$F$1,categories!$A$1:$B$1,0),FALSE) -> Mountain Bikes | G6: 1 | H6: 2899.99 | I6: 0.2 | J6: =G6*H6*(1-I6) -> 2319.992 | K6: =($H6-$M$7)/$M$9 -> 1.2473854
A7: 2 | B7: 1 | C7: 20 | D7: =VLOOKUP($C7,products!$A$1:$F$322,MATCH(order_items!$D$1,products!$A$1:$F$1,0),FALSE) -> Electra Townie Original 7D EQ - Women's - 2016 | E7: =VLOOKUP($C7,products!$A$1:$F$322,MATCH(order_items!$E$1,products!$A$1:$F$1,0),FALSE) -> 3 | F7: =VLOOKUP($E7,categories!$A$1:$B$8,MATCH(order_items!$F$1,categories!$A$1:$B$1,0),FALSE) -> Cruisers Bicycles | G7: 1 | H7: 599.99 | I7: 0.07 | J7: =G7*H7*(1-I7) -> 557.9907 | K7: =($H7-$M$7)/$M$9 -> -0.45297424 | L7: Average of price | M7: =AVERAGE(H:H) -> 1212.7079
A8: 2 | B8: 2 | C8: 16 | D8: =VLOOKUP($C8,products!$A$1:$F$322,MATCH(order_items!$D$1,products!$A$1:$F$1,0),FALSE) -> Electra Townie Original 7D EQ - 2016 | E8: =VLOOKUP($C8,products!$A$1:$F$322,MATCH(order_items!$E$1,products!$A$1:$F$1,0),FALSE) -> 3 | F8: =VLOOKUP($E8,categories!$A$1:$B$8,MATCH(order_items!$F$1,categories!$A$1:$B$1,0),FALSE) -> Cruisers Bicycles | G8: 2 | H8: 599.99 | I8: 0.05 | J8: =G8*H8*(1-I8) -> 1139.981 | K8: =($H8-$M$7)/$M$9 -> -0.45297424
A9: 3 | B9: 1 | C9: 3 | D9: =VLOOKUP($C9,products!$A$1:$F$322,MATCH(order_items!$D$1,products!$A$1:$F$1,0),FALSE) -> Surly Wednesday Frameset - 2016 | E9: =VLOOKUP($C9,products!$A$1:$F$322,MATCH(order_items!$E$1,products!$A$1:$F$1,0),FALSE) -> 6 | F9: =VLOOKUP($E9,categories!$A$1:$B$8,MATCH(order_items!$F$1,categories!$A$1:$B$1,0),FALSE) -> Mountain Bikes | G9: 1 | H9: 999.99 | I9: 0.05 | J9: =G9*H9*(1-I9) -> 949.9905 | K9: =($H9-$M$7)/$M$9 -> -0.15725952 | L9: Standard Deviation | M9: =_xlfn.STDEV.P(H:H) -> 1352.655
A10: 3 | B10: 2 | C10: 20 | D10: =VLOOKUP($C10,products!$A$1:$F$322,MATCH(order_items!$D$1,products!$A$1:$F$1,0),FALSE) -> Electra Townie Original 7D EQ - Women's - 2016 | E10: =VLOOKUP($C10,products!$A$1:$F$322,MATCH(order_items!$E$1,products!$A$1:$F$1,0),FALSE) -> 3 | F10: =VLOOKUP($E10,categories!$A$1:$B$8,MATCH(order_items!$F$1,categories!$A$1:$B$1,0),FALSE) -> Cruisers Bicycles | G10: 1 | H10: 599.99 | I10: 0.05 | J10: =G10*H10*(1-I10) -> 569.9905 | K10: =($H10-$M$7)/$M$9 -> -0.45297424
A11: 4 | B11: 1 | C11: 2 | D11: =VLOOKUP($C11,products!$A$1:$F$322,MATCH(order_items!$D$1,products!$A$1:$F$1,0),FALSE) -> Ritchey Timberwolf Frameset - 2016 | E11: =VLOOKUP($C11,products!$A$1:$F$322,MATCH(order_items!$E$1,products!$A$1:$F$1,0),FALSE) -> 6 | F11: =VLOOKUP($E11,categories!$A$1:$B$8,MATCH(order_items!$F$1,categories!$A$1:$B$1,0),FALSE) -> Mountain Bikes | G11: 2 | H11: 749.99 | I11: 0.1 | J11: =G11*H11*(1-I11) -> 1349.982 | K11: =($H11-$M$7)/$M$9 -> -0.34208122 | L11: Conditional formatting used and highlighted the highest outliers
A12: 5 | B12: 1 | C12: 10 | D12: =VLOOKUP($C12,products!$A$1:$F$322,MATCH(order_items!$D$1,products!$A$1:$F$1,0),FALSE) -> Surly Straggler - 2016 | E12: =VLOOKUP($C12,products!$A$1:$F$322,MATCH(order_items!$E$1,products!$A$1:$F$1,0),FALSE) -> 4 | F12: =VLOOKUP($E12,categories!$A$1:$B$8,MATCH(order_items!$F$1,categories!$A$1:$B$1,0),FALSE) -> Cyclocross Bicycles | G12: 2 | H12: 1549 | I12: 0.05 | J12: =G12*H12*(1-I12) -> 2943.1 | K12: =($H12-$M$7)/$M$9 -> 0.24861633
A13: 5 | B13: 2 | C13: 17 | D13: =VLOOKUP($C13,products!$A$1:$F$322,MATCH(order_items!$D$1,products!$A$1:$F$1,0),FALSE) -> Pure Cycles Vine 8-Speed - 2016 | E13: =VLOOKUP($C13,products!$A$1:$F$322,MATCH(order_items!$E$1,products!$A$1:$F$1,0),FALSE) -> 3 | F13: =VLOOKUP($E13,categories!$A$1:$B$8,MATCH(order_items!$F$1,categories!$A$1:$B$1,0),FALSE) -> Cruisers Bicycles | G13: 1 | H13: 429 | I13: 0.07 | J13: =G13*H13*(1-I13) -> 398.97 | K13: =($H13-$M$7)/$M$9 -> -0.57938489
A14: 5 | B14: 3 | C14: 26 | D14: =VLOOKUP($C14,products!$A$1:$F$322,MATCH(order_items!$D$1,products!$A$1:$F$1,0),FALSE) -> Electra Townie Original 7D EQ - 2016 | E14: =VLOOKUP($C14,products!$A$1:$F$322,MATCH(order_items!$E$1,products!$A$1:$F$1,0),FALSE) -> 2 | F14: =VLOOKUP($E14,categories!$A$1:$B$8,MATCH(order_items!$F$1,categories!$A$1:$B$1,0),FALSE) -> Comfort Bicycles | G14: 1 | H14: 599.99 | I14: 0.07 | J14: =G14*H14*(1-I14) -> 557.9907 | K14: =($H14-$M$7)/$M$9 -> -0.45297424
A15: 6 | B15: 1 | C15: 18 | D15: =VLOOKUP($C15,products!$A$1:$F$322,MATCH(order_items!$D$1,products!$A$1:$F$1,0),FALSE) -> Pure Cycles Western 3-Speed - Women's - 2015/2016 | E15: =VLOOKUP($C15,products!$A$1:$F$322,MATCH(order_items!$E$1,products!$A$1:$F$1,0),FALSE) -> 3 | F15: =VLOOKUP($E15,categories!$A$1:$B$8,MATCH(order_items!$F$1,categories!$A$1:$B$1,0),FALSE) -> Cruisers Bicycles | G15: 1 | H15: 449 | I15: 0.07 | J15: =G15*H15*(1-I15) -> 417.57 | K15: =($H15-$M$7)/$M$9 -> -0.56459915
A16: 6 | B16: 2 | C16: 12 | D16: =VLOOKUP($C16,products!$A$1:$F$322,MATCH(order_items!$D$1,products!$A$1:$F$1,0),FALSE) -> Electra Townie Original 21D - 2016 | E16: =VLOOKUP($C16,products!$A$1:$F$322,MATCH(order_items!$E$1,products!$A$1:$F$1,0),FALSE) -> 3 | F16: =VLOOKUP($E16,categories!$A$1:$B$8,MATCH(order_items!$F$1,categories!$A$1:$B$1,0),FALSE) -> Cruisers Bicycles | G16: 2 | H16: 549.99 | I16: 0.05 | J16: =G16*H16*(1-I16) -> 1044.981 | K16: =($H16-$M$7)/$M$9 -> -0.48993858
A17: 6 | B17: 3 | C17: 20 | D17: =VLOOKUP($C17,products!$A$1:$F$322,MATCH(order_items!$D$1,products!$A$1:$F$1,0),FALSE) -> Electra Townie Original 7D EQ - Women's - 2016 | E17: =VLOOKUP($C17,products!$A$1:$F$322,MATCH(order_items!$E$1,products!$A$1:$F$1,0),FALSE) -> 3 | F17: =VLOOKUP($E17,categories!$A$1:$B$8,MATCH(order_items!$F$1,categories!$A$1:$B$1,0),FALSE) -> Cruisers Bicycles | G17: 1 | H17: 599.99 | I17: 0.1 | J17: =G17*H17*(1-I17) -> 539.991 | K17: =($H17-$M$7)/$M$9 -> -0.45297424
A18: 6 | B18: 4 | C18: 3 | D18: =VLOOKUP($C18,products!$A$1:$F$322,MATCH(order_items!$D$1,products!$A$1:$F$1,0),FALSE) -> Surly Wednesday Frameset - 2016 | E18: =VLOOKUP($C18,products!$A$1:$F$322,MATCH(order_items!$E$1,products!$A$1:$F$1,0),FALSE) -> 6 | F18: =VLOOKUP($E18,categories!$A$1:$B$8,MATCH(order_items!$F$1,categories!$A$1:$B$1,0),FALSE) -> Mountain Bikes | G18: 2 | H18: 999.99 | I18: 0.07 | J18: =G18*H18*(1-I18) -> 1859.9814 | K18: =($H18-$M$7)/$M$9 -> -0.15725952
A19: 6 | B19: 5 | C19: 9 | D19: =VLOOKUP($C19,products!$A$1:$F$322,MATCH(order_items!$D$1,products!$A$1:$F$1,0),FALSE) -> Trek Conduit+ - 2016 | E19: =VLOOKUP($C19,products!$A$1:$F$322,MATCH(order_items!$E$1,products!$A$1:$F$1,0),FALSE) -> 5 | F19: =VLOOKUP($E19,categories!$A$1:$B$8,MATCH(order_items!$F$1,categories!$A$1:$B$1,0),FALSE) -> Electric Bikes | G19: 2 | H19: 2999.99 | I19: 0.07 | J19: =G19*H19*(1-I19) -> 5579.9814 | K19: =($H19-$M$7)/$M$9 -> 1.3213141
A20: 7 | B20: 1 | C20: 15 | D20: =VLOOKUP($C20,products!$A$1:$F$322,MATCH(order_items!$D$1,products!$A$1:$F$1,0),FALSE) -> Electra Moto 1 - 2016 | E20: =VLOOKUP($C20,products!$A$1:$F$322,MATCH(order_items!$E$1,products!$A$1:$F$1,0),FALSE) -> 3 | F20: =VLOOKUP($E20,categories!$A$1:$B$8,MATCH(order_items!$F$1,categories!$A$1:$B$1,0),FALSE) -> Cruisers Bicycles | G20: 1 | H20: 529.99 | I20: 0.07 | J20: =G20*H20*(1-I20) -> 492.8907 | K20: =($H20-$M$7)/$M$9 -> -0.50472432
A21: 7 | B21: 2 | C21: 3 | D21: =VLOOKUP($C21,products!$A$1:$F$322,MATCH(order_items!$D$1,products!$A$1:$F$1,0),FALSE) -> Surly Wednesday Frameset - 2016 | E21: =VLOOKUP($C21,products!$A$1:$F$322,MATCH(order_items!$E$1,products!$A$1:$F$1,0),FALSE) -> 6 | F21: =VLOOKUP($E21,categories!$A$1:$B$8,MATCH(order_items!$F$1,categories!$A$1:$B$1,0),FALSE) -> Mountain Bikes | G21: 1 | H21: 999.99 | I21: 0.1 | J21: =G21*H21*(1-I21) -> 899.991 | K21: =($H21-$M$7)/$M$9 -> -0.15725952
A22: 7 | B22: 3 | C22: 17 | D22: =VLOOKUP($C22,products!$A$1:$F$322,MATCH(order_items!$D$1,products!$A$1:$F$1,0),FALSE) -> Pure Cycles Vine 8-Speed - 2016 | E22: =VLOOKUP($C22,products!$A$1:$F$322,MATCH(order_items!$E$1,products!$A$1:$F$1,0),FALSE) -> 3 | F22: =VLOOKUP($E22,categories!$A$1:$B$8,MATCH(order_items!$F$1,categories!$A$1:$B$1,0),FALSE) -> Cruisers Bicycles | G22: 2 | H22: 429 | I22: 0.1 | J22: =G22*H22*(1-I22) -> 772.2 | K22: =($H22-$M$7)/$M$9 -> -0.57938489
A23: 8 | B23: 1 | C23: 22 | D23: =VLOOKUP($C23,products!$A$1:$F$322,MATCH(order_items!$D$1,products!$A$1:$F$1,0),FALSE) -> Electra Girl's Hawaii 1 (16-inch) - 2015/2016 | E23: =VLOOKUP($C23,products!$A$1:$F$322,MATCH(order_items!$E$1,products!$A$1:$F$1,0),FALSE) -> 1 | F23: =VLOOKUP($E23,categories!$A$1:$B$8,MATCH(order_items!$F$1,categories!$A$1:$B$1,0),FALSE) -> Children Bicycles | G23: 1 | H23: 269.99 | I23: 0.05 | J23: =G23*H23*(1-I23) -> 256.4905 | K23: =($H23-$M$7)/$M$9 -> -0.69693889
... A4723: 1615 | B4723: 3 | C4723: 182 | D4723: =VLOOKUP($C4723,products!$A$1:$F$322,MATCH(order_items!$D$1,products!$A$1:$F$1,0),FALSE) -> Trek Domane SL 5 Disc - 2018 | E4723: =VLOOKUP($C4723,products!$A$1:$F$322,MATCH(order_items!$E$1,products!$A$1:$F$1,0),FALSE) -> 7 | F4723: =VLOOKUP($E4723,categories!$A$1:$B$8,MATCH(order_items!$F$1,categories!$A$1:$B$1,0),FALSE) -> Road Bikes | G4723: 1 | H4723: 2499.99 | I4723: 0.2 | J4723: =G4723*H4723*(1-I4723) -> 1999.992 | K4723: =($H4723-$M$7)/$M$9 -> 0.95167069

Sheet products
A1: product_id | B1: product_name | C1: brand_id | D1: category_id | E1: model_year | F1: list_price
A2: 1 | B2: Trek 820 - 2016 | C2: 9 | D2: 6 | E2: 2016 | F2: 379.99
A3: 2 | B3: Ritchey Timberwolf Frameset - 2016 | C3: 5 | D3: 6 | E3: 2016 | F3: 749.99
A4: 3 | B4: Surly Wednesday Frameset - 2016 | C4: 8 | D4: 6 | E4: 2016 | F4: 999.99
A5: 4 | B5: Trek Fuel EX 8 29 - 2016 | C5: 9 | D5: 6 | E5: 2016 | F5: 2899.99
A6: 5 | B6: Heller Shagamaw Frame - 2016 | C6: 3 | D6: 6 | E6: 2016 | F6: 1320.99
A7: 6 | B7: Surly Ice Cream Truck Frameset - 2016 | C7: 8 | D7: 6 | E7: 2016 | F7: 469.99
A8: 7 | B8: Trek Slash 8 27.5 - 2016 | C8: 9 | D8: 6 | E8: 2016 | F8: 3999.99
A9: 8 | B9: Trek Remedy 29 Carbon Frameset - 2016 | C9: 9 | D9: 6 | E9: 2016 | F9: 1799.99
A10: 9 | B10: Trek Conduit+ - 2016 | C10: 9 | D10: 5 | E10: 2016 | F10: 2999.99
A11: 10 | B11: Surly Straggler - 2016 | C11: 8 | D11: 4 | E11: 2016 | F11: 1549
A12: 11 | B12: Surly Straggler 650b - 2016 | C12: 8 | D12: 4 | E12: 2016 | F12: 1680.99
A13: 12 | B13: Electra Townie Original 21D - 2016 | C13: 1 | D13: 3 | E13: 2016 | F13: 549.99
... A322: 321 | B322: Trek Checkpoint ALR Frameset - 2019 | C322: 9 | D322: 7 | E322: 2019 | F322: 3199.99

Sheet staffs
A1: staff_id | B1: first_name | C1: last_name | D1: email | E1: phone | F1: active | G1: store_id | H1: manager_id
A2: 1 | B2: Fabiola | C2: Jackson | D2: fabiola.jackson@bikes.shop | E2: (831) 555-5554 | F2: 1 | G2: 1 | H2: NA
A3: 2 | B3: Mireya | C3: Copeland | D3: mireya.copeland@bikes.shop | E3: (831) 555-5555 | F3: 1 | G3: 1 | H3: 1
A4: 3 | B4: Genna | C4: Serrano | D4: genna.serrano@bikes.shop | E4: (831) 555-5556 | F4: 1 | G4: 1 | H4: 2
A5: 4 | B5: Virgie | C5: Wiggins | D5: virgie.wiggins@bikes.shop | E5: (831) 555-5557 | F5: 1 | G5: 1 | H5: 2
A6: 5 | B6: Jannette | C6: David | D6: jannette.david@bikes.shop | E6: (516) 379-4444 | F6: 1 | G6: 2 | H6: 1
A7: 6 | B7: Marcelene | C7: Boyer | D7: marcelene.boyer@bikes.shop | E7: (516) 379-4445 | F7: 1 | G7: 2 | H7: 5
A8: 7 | B8: Venita | C8: Daniel | D8: venita.daniel@bikes.shop | E8: (516) 379-4446 | F8: 1 | G8: 2 | H8: 5
A9: 8 | B9: Kali | C9: Vargas | D9: kali.vargas@bikes.shop | E9: (972) 530-5555 | F9: 1 | G9: 3 | H9: 1
A10: 9 | B10: Layla | C10: Terrell | D10: layla.terrell@bikes.shop | E10: (972) 530-5556 | F10: 1 | G10: 3 | H10: 7
A11: 10 | B11: Bernardine | C11: Houston | D11: bernardine.houston@bikes.shop | E11: (972) 530-5557 | F11: 1 | G11: 3 | H11: 7

Sheet stocks
A1: store_id | B1: product_id | C1: quantity
A2: 1 | B2: 1 | C2: 27
A3: 1 | B3: 2 | C3: 5
A4: 1 | B4: 3 | C4: 6
A5: 1 | B5: 4 | C5: 23
A6: 1 | B6: 5 | C6: 22
A7: 1 | B7: 6 | C7: 0
A8: 1 | B8: 7 | C8: 8
A9: 1 | B9: 8 | C9: 0
A10: 1 | B10: 9 | C10: 11
A11: 1 | B11: 10 | C11: 15
A12: 1 | B12: 11 | C12: 8
A13: 1 | B13: 12 | C13: 16
... A940: 3 | B940: 313 | C940: 0

Sheet stores
A1: store_id | B1: store_name | C1: phone | D1: email | E1: street | F1: city | G1: state | H1: zip_code
A2: 1 | B2: Santa Cruz Bikes | C2: (831) 476-4321 | D2: santacruz@bikes.shop | E2: 3700 Portola Drive | F2: Santa Cruz | G2: CA | H2: 95060
A3: 2 | B3: Baldwin Bikes | C3: (516) 379-8888 | D3: baldwin@bikes.shop | E3: 4200 Chestnut Lane | F3: Baldwin | G3: NY | H3: 11432
A4: 3 | B4: Rowlett Bikes | C4: (972) 530-5555 | D4: rowlett@bikes.shop | E4: 8000 Fairway Avenue | F4: Rowlett | G4: TX | H4: 75088
